<?xml version="1.0" encoding="utf-8"?>
<contentList>
	<content contentuid="h0e9fcdbbg48cdg4c58gbfdbg0b29015e4eaa" version="1">Si tuviera dinero, igual podría permitirme un poco de superioridad moral. Toda tuya, heroína.</content>
	<content contentuid="h12aba278g8849g4525gb694g3651609f5866" version="1">Aunque somos extrañas compañeras de cama. Muy bien.</content>
	<content contentuid="h1a11119egcc77g4473g92f5gf670f2429ca0" version="1">Así que lárgate o demuéstrame de qué estás hecha.</content>
	<content contentuid="h1ff7cc4dg5cd7g4e66g95adg0e1eab2970d1" version="2">Ay, ya lo hago. Son la clase de batallas que una cachorrita como tú tan solo ve en sus pesadillas.</content>
	<content contentuid="h34230b78geee7g4a05g8ca8g83a69db32c99" version="6">Si eres tan mordedora como ladradora, igual nos llevamos bien y todo. Vale que soy peligrosa, pero no tengo nada contra ti.</content>
	<content contentuid="h88030eaageadag4170g9c8fgbb663ebf97c2" version="1">No pienso darle un segundo aviso a una perra traicionera como tú, así que nada de movimientos bruscos.</content>
	<content contentuid="h98c4a040g000cg4b43gbb30g9e4937f691e9" version="2">Lárgate o demuéstrame de qué estás hecha.</content>
	<content contentuid="ha092efb0g9640g4af4g9c61g20e211f3769c" version="2">Ni tú ni yo hemos aceptado muchas de las cosas que nos han ocurrido últimamente. Puede que juntas consigamos cambiarlo.</content>
	<content contentuid="hbb7d0141g3d51g40bfgbb62gce7726de27a0" version="5">Hum. Si eres tan mordedora como ladradora, igual nos llevamos bien y todo. Puede que incluso tenga un trabajito para ti.&lt;br&gt;</content>
	<content contentuid="hd086b5dcg9d5bg4790gb2acg7f01c38cf6d0" version="1">La vergüenza no se come, hermana. Es mejor aprenderlo antes de que empiecen a rugirte las tripas.</content>
	<content contentuid="hf4d15e5fg85a8g401bg8f22gd98425848b39" version="1">Me parece bien. Pero una líder siempre debe tener presente cualquier posible conflicto, ¿verdad?</content>
</contentList>